nbDevTools/__init__.py
nbDevTools/cmd_shell.py
nbDevTools/dev.py
nbDevTools/py.typed
nbDevTools/nbCom/__init__.py
nbDevTools/nbCom/jupyter.py
nbDevTools/nbFlask/__init__.py
nbDevTools/nbFlask/py.typed
nbDevTools/pyClosure/__init__.py
nbDevTools/pyClosure/examples.py
nbDevTools/pyClosure/flask_app.py
nbDevTools/pyClosure/py.typed
nbDevTools/pyClosure/tools.py
nbDevTools-0.0.3.dist-info/METADATA
nbDevTools-0.0.3.dist-info/WHEEL
nbDevTools-0.0.3.dist-info/top_level.txt
nbDevTools-0.0.3.dist-info/RECORD
