Metadata-Version: 2.1
Name: nbDevTools
Version: 0.0.3
Summary: Local Script Tools
Author-email: Christoph Chester Cury <cury.grupos@gmail.com>
License: MIT
Classifier: Programming Language :: Python :: 3
Classifier: License :: OSI Approved :: MIT License
Classifier: Operating System :: OS Independent
Requires-Python: >=3.6
